pytiles/__init__.py
pytiles/cli.py
pytiles/getmap.py
pytiles/server.py
pytiles-0.0.3.dist-info/METADATA
pytiles-0.0.3.dist-info/WHEEL
pytiles-0.0.3.dist-info/entry_points.txt
pytiles-0.0.3.dist-info/top_level.txt
pytiles-0.0.3.dist-info/RECORD
