Metadata-Version: 2.1
Name: pytiles
Version: 0.0.3
Summary: python OGC WMS server
Home-page: UNKNOWN
Author: Kobe De Decker
Author-email: kobededecker@gmail.com
License: MIT
Platform: UNKNOWN
Requires-Dist: rasterio
Requires-Dist: pyfiglet
Requires-Dist: termcolor
